spaceboi.py
spaceboi-0.1.4.dist-info/LICENSE
spaceboi-0.1.4.dist-info/METADATA
spaceboi-0.1.4.dist-info/WHEEL
spaceboi-0.1.4.dist-info/entry_points.txt
spaceboi-0.1.4.dist-info/top_level.txt
spaceboi-0.1.4.dist-info/RECORD
