Metadata-Version: 2.1
Name: spaceboi
Version: 0.1.4
Summary: A radio satellite event tracker.
Home-page: https://github.com/ericpar234/spaceboi
Author: ericpar234
Classifier: Programming Language :: Python :: 3
Classifier: License :: OSI Approved :: MIT License
Classifier: Operating System :: OS Independent
Requires-Python: >=3.10
License-File: LICENSE
Requires-Dist: skyfield
Requires-Dist: requests
Requires-Dist: pytz
Requires-Dist: PyQt5
Requires-Dist: matplotlib
Requires-Dist: numpy
Requires-Dist: Basemap
Requires-Dist: darkdetect
Requires-Dist: icalendar
